setup.py
persistablemd5/__init__.py
persistablemd5/md5hack.py
persistablemd5/persistablemd5.py
persistablemd5.egg-info/PKG-INFO
persistablemd5.egg-info/SOURCES.txt
persistablemd5.egg-info/dependency_links.txt
persistablemd5.egg-info/top_level.txt
persistablemd5/test/__init__.py
persistablemd5/test/test_persistablemd5.py