Metadata-Version: 1.0
Name: persistablemd5
Version: 0.0.2
Summary: Adds get- and setstate methods to hashlib.md5
Home-page: https://github.com/team-zoltan/persistablemd5
Author: Team Zoltan
Author-email: zoltan@spideroak.com
License: MIT
Platform: UNKNOWN
Classifier: Intended Audience :: Developers
Classifier: License :: OSI Approved :: MIT License
Classifier: Programming Language :: Python
Classifier: Topic :: Software Development :: Libraries :: Python Modules
